packer_ami_workflow/__init__.py
packer_ami_workflow/_version.py
packer_ami_workflow/api.py
packer_ami_workflow/builder.py
packer_ami_workflow/dynamodb.py
packer_ami_workflow/ec2.py
packer_ami_workflow/logger.py
packer_ami_workflow/packer.py
packer_ami_workflow/param.py
packer_ami_workflow/paths.py
packer_ami_workflow/workspace.py
packer_ami_workflow/docs/__init__.py
packer_ami_workflow/tests/__init__.py
packer_ami_workflow/tests/example.py
packer_ami_workflow/tests/helper.py
packer_ami_workflow/vendor/__init__.py
packer_ami_workflow/vendor/jsonutils.py
packer_ami_workflow/vendor/nested_logger.py
packer_ami_workflow/vendor/pytest_cov_helper.py
packer_ami_workflow-0.1.2.dist-info/AUTHORS.rst
packer_ami_workflow-0.1.2.dist-info/LICENSE.txt
packer_ami_workflow-0.1.2.dist-info/METADATA
packer_ami_workflow-0.1.2.dist-info/WHEEL
packer_ami_workflow-0.1.2.dist-info/top_level.txt
packer_ami_workflow-0.1.2.dist-info/RECORD
