Metadata-Version: 2.1
Name: packer_ami_workflow
Version: 0.1.2
Summary: A workflow for large scale Amazon Machine Image build project.
Home-page: https://github.com/MacHu-GWU/packer_ami_workflow-project
Download-URL: https://pypi.python.org/pypi/packer_ami_workflow/0.1.2#downloads
Author: Sanhe Hu
Author-email: husanhe@gmail.com
Maintainer: Sanhe Hu
Maintainer-email: husanhe@gmail.com
License: MIT
Platform: Windows
Platform: MacOS
Platform: Unix
Classifier: Development Status :: 4 - Beta
Classifier: Intended Audience :: Developers
Classifier: License :: OSI Approved :: MIT License
Classifier: Natural Language :: English
Classifier: Operating System :: Microsoft :: Windows
Classifier: Operating System :: MacOS
Classifier: Operating System :: Unix
Classifier: Programming Language :: Python
Classifier: Programming Language :: Python :: 3.8
Classifier: Programming Language :: Python :: 3.9
Classifier: Programming Language :: Python :: 3.10
Classifier: Programming Language :: Python :: 3.11
Classifier: Programming Language :: Python :: 3.12
Classifier: Programming Language :: Python :: 3 :: Only
Requires-Python: >=3.8
License-File: LICENSE.txt
License-File: AUTHORS.rst
Requires-Dist: pathlib-mate <2.0.0,>=1.3.2
Requires-Dist: botocore <2.0.0,>=1.33.13
Requires-Dist: boto3 <2.0.0,>=1.33.13
Requires-Dist: boto-session-manager <2.0.0,>=1.7.2
Requires-Dist: aws-console-url <2.0.0,>=1.4.1
Requires-Dist: jinja2 <4.0.0,>=3.0.3
Requires-Dist: pynamodb <7.0.0,>=6.0.0
Requires-Dist: pynamodb-mate <7.0.0.0,>=6.0.0.3
Requires-Dist: simple-aws-ec2 <1.0.0,>=0.7.3
Provides-Extra: docs
Requires-Dist: Sphinx ==5.3.0 ; extra == 'docs'
Requires-Dist: sphinx-jinja ==2.0.2 ; extra == 'docs'
Requires-Dist: sphinx-copybutton ==0.5.1 ; extra == 'docs'
Requires-Dist: sphinx-design ==0.5.0 ; extra == 'docs'
Requires-Dist: furo ==2023.03.27 ; extra == 'docs'
Requires-Dist: nbsphinx ==0.8.12 ; extra == 'docs'
Requires-Dist: rstobj ==1.2.1 ; extra == 'docs'
Requires-Dist: pygments ==2.15.1 ; extra == 'docs'
Requires-Dist: ipython ==8.10.0 ; extra == 'docs'
Requires-Dist: docfly ==2.0.3 ; extra == 'docs'
Provides-Extra: tests
Requires-Dist: pytest ; extra == 'tests'
Requires-Dist: pytest-cov ; extra == 'tests'
